dtcli/__init__.py
dtcli/clear.py
dtcli/cli.py
dtcli/config.py
dtcli/config.yaml
dtcli/ls.py
dtcli/ps.py
dtcli/pull.py
dtcli/scout.py
dtcli/src/functions.py
dtcli/utilities/cadcclient.py
dtcli/utilities/utilities.py
datatrail_cli-0.9.2.dist-info/METADATA
datatrail_cli-0.9.2.dist-info/WHEEL
datatrail_cli-0.9.2.dist-info/entry_points.txt
datatrail_cli-0.9.2.dist-info/licenses/LICENSE
datatrail_cli-0.9.2.dist-info/RECORD
