Metadata-Version: 2.4
Name: datatrail-cli
Version: 0.9.2
Summary: CHIME/FRB Datatrail CLI
License: MIT
License-File: LICENSE
Author: CHIME FRB Project Office
Requires-Python: >=3.8, !=2.7.*, !=3.0.*, !=3.1.*, !=3.2.*, !=3.3.*, !=3.4.*, !=3.5.*, !=3.6.*, !=3.7.*
Classifier: License :: OSI Approved :: MIT License
Classifier: Programming Language :: Python :: 3
Classifier: Programming Language :: Python :: 3.10
Classifier: Programming Language :: Python :: 3.11
Classifier: Programming Language :: Python :: 3.12
Classifier: Programming Language :: Python :: 3.13
Classifier: Programming Language :: Python :: 3.14
Requires-Dist: cadcdata (>=2.5.0,<3.0.0)
Requires-Dist: cadctap (>=0.9.11,<0.10.0)
Requires-Dist: cadcutils (>=1.5.1.1,<2.0.0.0)
Requires-Dist: click (>=8.1.3,<9.0.0)
Requires-Dist: click-aliasing (>=1.0.0,<2.0.0)
Requires-Dist: dill (>=0.3.6,<0.4.0)
Requires-Dist: lxml (>=4.9.2,<5.0.0)
Requires-Dist: mergedeep (>=1.3.4,<2.0.0)
Requires-Dist: pyaml (>=21.10.1,<22.0.0)
Requires-Dist: requests (>=2.29.0,<3.0.0)
Requires-Dist: rich (>=13.3.5,<14.0.0)
